LICENSE
MANIFEST.in
README.rst
setup.cfg
setup.py
src/django_static_compiler.egg-info/PKG-INFO
src/django_static_compiler.egg-info/SOURCES.txt
src/django_static_compiler.egg-info/dependency_links.txt
src/django_static_compiler.egg-info/not-zip-safe
src/django_static_compiler.egg-info/requires.txt
src/django_static_compiler.egg-info/top_level.txt
src/static_compiler/__init__.py
src/static_compiler/constants.py
src/static_compiler/management/__init__.py
src/static_compiler/management/commands/__init__.py
src/static_compiler/management/commands/compilestatic.py
src/static_compiler/templatetags/__init__.py
src/static_compiler/templatetags/static_compiler.py