Metadata-Version: 1.0
Name: django-static-compiler
Version: 0.2.3
Summary: A static file compiler for Django
Home-page: http://github.com/dcramer/django-static-compiler
Author: David Cramer
Author-email: dcramer@gmail.com
License: Apache License 2.0
Platform: UNKNOWN
Classifier: Framework :: Django
Classifier: Intended Audience :: Developers
Classifier: Intended Audience :: System Administrators
Classifier: Operating System :: OS Independent
Classifier: Topic :: Software Development
